lemniscat/plugin/awscli/__init__.py
lemniscat/plugin/awscli/awscli.py
lemniscat/plugin/awscli/filestore.py
lemniscat/plugin/awscli/main.py
lemniscat/plugin/awscli/plugin.yaml
lemniscat/plugin/awscli/requirements.txt
lemniscat.plugin.awscli-0.3.0.dist-info/LICENSE
lemniscat.plugin.awscli-0.3.0.dist-info/METADATA
lemniscat.plugin.awscli-0.3.0.dist-info/WHEEL
lemniscat.plugin.awscli-0.3.0.dist-info/top_level.txt
lemniscat.plugin.awscli-0.3.0.dist-info/RECORD
